tests/__init__.py
tests/test_account.py
tests/test_api.py
tests/test_market_hours.py
tests/mock_api/__init__.py
tests/mock_api/account_responses.py
tests/mock_api/mock_api.py
tests/mock_api/order_responses.py
tests/mock_api/quote_responses.py
tests/order/__init__.py
tests/order/test_base_order.py
tests/quote/__init__.py
tests/quote/test_data_frame_quote.py
tests/quote/test_multi_quote.py
tests/quote/test_quote.py
wetrade/__init__.py
wetrade/__main__.py
wetrade/account.py
wetrade/api.py
wetrade/market_hours.py
wetrade/user_session.py
wetrade/utils.py
wetrade/order/__init__.py
wetrade/order/base_order.py
wetrade/order/basic_order_types.py
wetrade/order/converting_stop_order.py
wetrade/order/lookup_msg.py
wetrade/project_template/Dockerfile
wetrade/project_template/__init__.py
wetrade/project_template/main.py
wetrade/project_template/new_project.py
wetrade/project_template/requirements.txt
wetrade/project_template/settings.py
wetrade/project_template/trading_session.py
wetrade/quote/__init__.py
wetrade/quote/data_frame_quote.py
wetrade/quote/multi_quote.py
wetrade/quote/quote.py
wetrade-1.0.3.dist-info/licenses/LICENSE
wetrade-1.0.3.dist-info/METADATA
wetrade-1.0.3.dist-info/WHEEL
wetrade-1.0.3.dist-info/top_level.txt
wetrade-1.0.3.dist-info/RECORD
