Metadata-Version: 2.4
Name: wetrade
Version: 1.0.3
Summary: An E-Trade python library built for active stock trading
Home-page: https://github.com/mason-krause/wetrade
Author: Mason Krause
Requires-Python: >=3.7
License-File: LICENSE
Requires-Dist: authlib
Requires-Dist: playwright==1.44.0
Requires-Dist: urllib3==1.26.16
Requires-Dist: xmltodict
Requires-Dist: pytz
Requires-Dist: pyotp==2.9.0
Requires-Dist: google-cloud-logging
Requires-Dist: google-cloud-storage
Requires-Dist: google-cloud-secret-manager
Requires-Dist: polars
Requires-Dist: pandas
Requires-Dist: pyarrow
Provides-Extra: dev
Requires-Dist: pytest; extra == "dev"
Requires-Dist: pytest-timeout; extra == "dev"
Requires-Dist: sphinx; extra == "dev"
Requires-Dist: sphinx_rtd_theme; extra == "dev"
Dynamic: author
Dynamic: description
Dynamic: description-content-type
Dynamic: home-page
Dynamic: license-file
Dynamic: provides-extra
Dynamic: requires-dist
Dynamic: requires-python
Dynamic: summary
